{
  "0" : {
    "Category" : "hair",
    "Description" : "I love shile bello too",
    "Facebook" : "jdavid",
    "FirstName" : "Stanley",
    "ImageURL" : "https://firebasestorage.googleapis.com/v0/b/rimmi-ff8d1.appspot.com/o/stanleyprofilepix.png?alt=media&token=4937f99c-cbf3-493a-9417-36d41cf96bbc",
    "LastName" : "Wilson",
    "MainPhone" : "234898234",
    "OfficeCity" : "Kaduna",
    "OfficeCountry" : "NGN",
    "OfficeLine1" : "Ugwan rimi",
    "OfficeState" : "Kaduna",
    "Services" : "mumu, Barber, Braids,  Okada, Pedicure",
    "Twitter" : "jdavid",
    "VendorID" : "1",
    "YearsAsMember" : "20",
    "latitude" : 10.609319,
    "longitude" : 7.429504
  },
  "1" : {
    "Description" : "Don’t worry I will take care of you, not creepy at all",
    "Facebook" : "ifamb",
    "FirstName" : "Ibiwunmi",
    "ImageURL" : "https://firebasestorage.googleapis.com/v0/b/rimmi-ff8d1.appspot.com/o/oreprofilepix.png?alt=media&token=6b60874b-e660-485b-9b1e-82369f042fac",
    "LastName" : "Fambegbe",
    "MainPhone" : "234898234",
    "OfficeCity" : "Lagos",
    "OfficeCountry" : "NGN",
    "OfficeLine1" : "Ikeja",
    "OfficeState" : "Lagos",
    "Services" : "Barber, Braids,  Okada, ",
    "Twitter" : "ifamb",
    "VendorID" : "2",
    "YearsAsMember" : "20",
    "latitude" : 10.609319,
    "longitude" : 6.429504
  },
  "2" : {
    "Description" : "Don’t worry I will take care of you, not creepy at all",
    "Facebook" : "jdavid",
    "FirstName" : "Titilope",
    "ImageURL" : "https://firebasestorage.googleapis.com/v0/b/rimmi-ff8d1.appspot.com/o/jesuyeprofilepix.png?alt=media&token=9573eea6-a943-4846-a893-975133df8251",
    "LastName" : "Olubiyi",
    "MainPhone" : "234898234",
    "OfficeCity" : "Ikeja",
    "OfficeCountry" : "NGN",
    "OfficeLine1" : "Lekki",
    "OfficeState" : "Lagos",
    "Services" : "Barber, Braids,  Okada, Drycleaning, cooking, wedding planner, event planner ",
    "Twitter" : "tolubiti",
    "VendorID" : "3",
    "YearsAsMember" : "20",
    "latitude" : 6.458985,
    "longitude" : 3.601521
  },
  "3" : {
    "Description" : "Im as gay as the day is long",
    "Facebook" : "sbello",
    "FirstName" : "Abdul",
    "ImageURL" : "https://firebasestorage.googleapis.com/v0/b/rimmi-ff8d1.appspot.com/o/shileprofilepix.png?alt=media&token=ec312bd6-8563-459b-bcc1-b0c3523e661b",
    "LastName" : "Bello",
    "MainPhone" : "234898234",
    "OfficeCity" : "Kaduna",
    "OfficeCountry" : "NGN",
    "OfficeLine1" : "Barnawa",
    "OfficeState" : "Lagos",
    "Services" : "mumu, Barber, Braids,  Okada, ",
    "Twitter" : "sbello",
    "VendorID" : "4",
    "YearsAsMember" : "20",
    "latitude" : 10.609319,
    "longitude" : 4.429504
  },
  "4" : {
    "Description" : "Don’t worry I will take care of you, not creepy at all",
    "Facebook" : "jdavid",
    "FirstName" : "Jesuye",
    "ImageURL" : "https://firebasestorage.googleapis.com/v0/b/rimmi-ff8d1.appspot.com/o/jesuyeprofilepix.png?alt=media&token=9573eea6-a943-4846-a893-975133df8251",
    "LastName" : "David",
    "MainPhone" : "234898234",
    "OfficeCity" : "Kaduna",
    "OfficeCountry" : "NGN",
    "OfficeLine1" : "Barnawa",
    "OfficeState" : "Kaduna",
    "Services" : "Barber, Braids,  Okada, ",
    "Twitter" : "jdavid",
    "VendorID" : "5",
    "YearsAsMember" : "20",
    "latitude" : 10.609319,
    "longitude" : 3.429504
  },
  "5" : {
    "Description" : "I love Jesus",
    "Facebook" : "jdavid",
    "FirstName" : "Tolulope",
    "ImageURL" : "https://firebasestorage.googleapis.com/v0/b/rimmi-ff8d1.appspot.com/o/toluprofilepix.png?alt=media&token=d71d21e5-edc9-49a4-866c-0835bfa04057",
    "LastName" : "Ibikunle",
    "MainPhone" : "234898234",
    "OfficeCity" : "Tanke",
    "OfficeCountry" : "NGN",
    "OfficeLine1" : "University of Ilorin",
    "OfficeState" : "Kwara",
    "Services" : "mumu, electrician,Barber, Braids,  Okada, ",
    "Twitter" : "jdavid",
    "VendorID" : "6",
    "YearsAsMember" : "20",
    "latitude" : 9.609319,
    "longitude" : 3.429504
  },
  "6" : {
    "Description" : "Don’t worry I will take care of you, not creepy at all",
    "Facebook" : "jdavid",
    "FirstName" : "Jesuye",
    "ImageURL" : "https://firebasestorage.googleapis.com/v0/b/rimmi-ff8d1.appspot.com/o/jesuyeprofilepix.png?alt=media&token=9573eea6-a943-4846-a893-975133df8251",
    "LastName" : "David",
    "MainPhone" : "234898234",
    "OfficeCity" : "Kaduna",
    "OfficeCountry" : "NGN",
    "OfficeLine1" : "Barnawa",
    "OfficeState" : "Kaduna",
    "Services" : "Barber, Braids,  Okada, ",
    "Twitter" : "jdavid",
    "VendorID" : "7",
    "YearsAsMember" : "20",
    "latitude" : 8.609319,
    "longitude" : 3.429504
  },
  "7" : {
    "Category" : "hair",
    "Description" : "Don’t worry I will take care of you, not creepy at all",
    "Facebook" : "jdavid",
    "FirstName" : "Jesuye",
    "ImageURL" : "https://firebasestorage.googleapis.com/v0/b/rimmi-ff8d1.appspot.com/o/jesuyeprofilepix.png?alt=media&token=9573eea6-a943-4846-a893-975133df8251",
    "LastName" : "David",
    "MainPhone" : "234898234",
    "OfficeCity" : "Kaduna",
    "OfficeCountry" : "NGN",
    "OfficeLine1" : "Barnawa",
    "OfficeState" : "Kaduna",
    "Services" : "Barber, Braids,  Okada, ",
    "Twitter" : "jdavid",
    "VendorID" : "8",
    "YearsAsMember" : "20",
    "latitude" : 7.609319,
    "longitude" : 3.429504
  },
  "8" : {
    "Description" : "Don’t worry I will take care of you, not creepy at all",
    "Facebook" : "jdavid",
    "FirstName" : "Jesuye",
    "ImageURL" : "https://firebasestorage.googleapis.com/v0/b/rimmi-ff8d1.appspot.com/o/jesuyeprofilepix.png?alt=media&token=9573eea6-a943-4846-a893-975133df8251",
    "LastName" : "David",
    "MainPhone" : "234898234",
    "OfficeCity" : "Kaduna",
    "OfficeCountry" : "NGN",
    "OfficeLine1" : "Barnawa",
    "OfficeState" : "Kaduna",
    "Services" : "Barber, Braids,  Okada, ",
    "Twitter" : "jdavid",
    "VendorID" : "9",
    "YearsAsMember" : "20",
    "latitude" : 8.909319,
    "longitude" : 3.809504
  },
  "9" : {
    "Description" : "I love Ibadan! Ibadan forever",
    "Facebook" : "tdairo",
    "FirstName" : "Tosin",
    "ImageURL" : "https://firebasestorage.googleapis.com/v0/b/rimmi-ff8d1.appspot.com/o/tosinprofilepix.png?alt=media&token=093a77f9-fadd-4848-a0de-011ef4bd5112",
    "LastName" : "Dairo",
    "MainPhone" : "234898234",
    "OfficeCity" : "Ibandan",
    "OfficeCountry" : "NGN",
    "OfficeLine1" : "Dairo Street",
    "OfficeState" : "Oyo",
    "Services" : "pedicure, manicure,Barber, Braids,  Okada, ",
    "Twitter" : "tdairo",
    "VendorID" : "10",
    "YearsAsMember" : "20",
    "latitude" : 9.129319,
    "longitude" : 4.999504
  },
  "10" : {
    "Description" : "Don’t worry I will take care of you, not creepy at all",
    "Facebook" : "jdavid",
    "FirstName" : "Jesuye",
    "ImageURL" : "https://firebasestorage.googleapis.com/v0/b/rimmi-ff8d1.appspot.com/o/jesuyeprofilepix.png?alt=media&token=9573eea6-a943-4846-a893-975133df8251",
    "LastName" : "David",
    "MainPhone" : "234898234",
    "OfficeCity" : "Kaduna",
    "OfficeCountry" : "NGN",
    "OfficeLine1" : "Barnawa",
    "OfficeState" : "Kaduna",
    "Services" : "Barber, Braids,  Okada, ",
    "Twitter" : "jdavid",
    "VendorID" : "11",
    "YearsAsMember" : "20",
    "latitude" : 7.129319,
    "longitude" : 4.999504
  },
  "11" : {
    "Description" : "Don’t worry I will take care of you, not creepy at all",
    "Facebook" : "jdavid",
    "FirstName" : "Jesuye",
    "ImageURL" : "https://i.picsum.photos/id/1026/4621/3070.jpg?hmac=OJ880cIneqAKIwHbYgkRZxQcuMgFZ4IZKJasZ5c5Wcw",
    "LastName" : "David",
    "MainPhone" : "234898234",
    "OfficeCity" : "Kaduna",
    "OfficeCountry" : "NGN",
    "OfficeLine1" : "Barnawa",
    "OfficeState" : "Kaduna",
    "Services" : "Barber, Braids,  Okada, ",
    "Twitter" : "jdavid",
    "VendorID" : "12",
    "YearsAsMember" : "20",
    "latitude" : 8.129319,
    "longitude" : 6.999504
  },
  "TShRmJdAbQfDXSSzqCPZF8gCX7D2" : {
    "Category" : "car service,hair,",
    "Description" : "",
    "Facebook" : "",
    "FirstName" : "Sam Jam",
    "LastName" : "Sam Jam",
    "MainPhone" : "",
    "OfficeCity" : "",
    "OfficeLine1" : "",
    "OfficeState" : "",
    "OfficeZip" : "",
    "Services" : "",
    "Twitter" : "",
    "VendorID" : "TShRmJdAbQfDXSSzqCPZF8gCX7D2",
    "latitude" : 8.129319,
    "longitide" : 6.999504
  }
}
